{
    "/public/js/homepage.js": "/public/js/homepage.js?id=648615373c6666872fde",
    "/public/css/homepage.css": "/public/css/homepage.css?id=8a0818a7c79bfab43a70",
    "/public/css/announcement/photopage.css": "/public/css/announcement/photopage.css?id=68b329da9893e34099c7",
    "/public/css/announcement/announcement.css": "/public/css/announcement/announcement.css?id=73d050b57087b3999a81",
    "/public/img/search.gif": "/public/img/search.gif?id=bfad1bbb20445fece057",
    "/public/img/on-flag.gif": "/public/img/on-flag.gif?id=d694c042ccd0cf294595",
    "/public/img/off-flag.gif": "/public/img/off-flag.gif?id=59d62798bd9ab101f24a"
}
